simplify_rest_framework/__init__.py
simplify_rest_framework/apps.py
simplify_rest_framework/model_factory.py
simplify_rest_framework/permissions.py
simplify_rest_framework/serializer.py
simplify_rest_framework/view_set.py
simplify_rest_framework/views.py
simplify_rest_framework-0.12.2.dist-info/LICENSE
simplify_rest_framework-0.12.2.dist-info/METADATA
simplify_rest_framework-0.12.2.dist-info/WHEEL
simplify_rest_framework-0.12.2.dist-info/top_level.txt
simplify_rest_framework-0.12.2.dist-info/RECORD
