Metadata-Version: 2.1
Name: simplify-rest-framework
Version: 0.12.2
Summary: Simplified version of django rest framework
Home-page: https://github.com/mahbd/simplify-rest-framework
Author: Mahmudul Alam
Author-email: mahmudula2000@gmail.com
License: MIT
Platform: UNKNOWN
Classifier: License :: OSI Approved :: MIT License
Classifier: Operating System :: OS Independent
Classifier: Environment :: Web Environment
Classifier: Programming Language :: Python :: 3
Classifier: Programming Language :: Python :: 3.10
Classifier: Framework :: Django
Classifier: Framework :: Django :: 4.0
License-File: LICENSE
Requires-Dist: django (>=3.2.0)
Requires-Dist: django-filter (>=21.1.0)
